Verilog/Stage 3/Tutorial_AsyncUPcounter/cntr.v
`timescale 1ns/1ps
module SimpleUPcounter (
    input wire rst,clk,
    output reg[3:0] count
);

always @(posedge clk or posedge rst ) begin
    if(rst)
        count<=4'b0000;
    else if(clk)
        count<=count +1;      
end   
endmodule

Verilog/Stage 3/Tutorial_AsyncUPcounter/cntrTB.v
`timescale 1ns/1ps
module cntrtb;
reg clk,rst;
wire[3:0] count;
SimpleUPcounter dut(
    .clk(clk),
    .rst(rst),
    .count(count)
);
initial rst=1;
initial clk=0;
always #5 clk=~clk;
initial begin
    rst=0;
    $display("Clock\t\tReset\t\tCount");
    $monitor("%b\t\t%b\t\t%b\t\t",clk,rst,count);
    #20;
    rst=1;
    #20;
    rst=0;
    #200;
    $finish;
end
initial begin
    $dumpfile("cntr.vcd");
    $dumpvars(0,cntrtb);
end
endmodule

Verilog/Stage 3/Tutorial_AsyncUPcounter/cntr.vcd
$date
	Wed May 21 17:48:09 2025
$end
$version
	Icarus Verilog
$end
$timescale
	1ps
$end
$scope module cntrtb $end
$var wire 4 ! count [3:0] $end
$var reg 1 " clk $end
$var reg 1 # rst $end
$scope module dut $end
$var wire 1 " clk $end
$var wire 1 # rst $end
$var reg 4 $ count [3:0] $end
$upscope $end
$upscope $end
$enddefinitions $end
$comment Show the parameter values. $end
$dumpall
$end
#0
$dumpvars
bx $
0#
0"
bx !
$end
#5000
1"
#10000
0"
#15000
1"
#20000
b0 !
b0 $
0"
1#
#25000
1"
#30000
0"
#35000
1"
#40000
0"
0#
#45000
b1 !
b1 $
1"
#50000
0"
#55000
b10 !
b10 $
1"
#60000
0"
#65000
b11 !
b11 $
1"
#70000
0"
#75000
b100 !
b100 $
1"
#80000
0"
#85000
b101 !
b101 $
1"
#90000
0"
#95000
b110 !
b110 $
1"
#100000
0"
#105000
b111 !
b111 $
1"
#110000
0"
#115000
b1000 !
b1000 $
1"
#120000
0"
#125000
b1001 !
b1001 $
1"
#130000
0"
#135000
b1010 !
b1010 $
1"
#140000
0"
#145000
b1011 !
b1011 $
1"
#150000
0"
#155000
b1100 !
b1100 $
1"
#160000
0"
#165000
b1101 !
b1101 $
1"
#170000
0"
#175000
b1110 !
b1110 $
1"
#180000
0"
#185000
b1111 !
b1111 $
1"
#190000
0"
#195000
b0 !
b0 $
1"
#200000
0"
#205000
b1 !
b1 $
1"
#210000
0"
#215000
b10 !
b10 $
1"
#220000
0"
#225000
b11 !
b11 $
1"
#230000
0"
#235000
b100 !
b100 $
1"
